bloom/__init__.py
bloom/settings.py
bloom/models/__init__.py
bloom/models/base.py
bloom/models/exceptons.py
BloomORM-1.0.3.dist-info/LICENSE
BloomORM-1.0.3.dist-info/METADATA
BloomORM-1.0.3.dist-info/WHEEL
BloomORM-1.0.3.dist-info/top_level.txt
BloomORM-1.0.3.dist-info/RECORD
