Metadata-Version: 2.1
Name: BloomORM
Version: 1.0.3
Summary: Model method update del
Home-page: https://github.com/JenIK-s/BloomORM-json-project
Author: JenIKs
Author-email: fertuv68@gmail.com
Project-URL: Documentation, https://github.com/JenIK-s/BloomORM-json-project
Keywords: Json ORM
Classifier: Programming Language :: Python :: 3.11
Classifier: License :: OSI Approved :: MIT License
Classifier: Operating System :: OS Independent
Requires-Python: >=3.7
License-File: LICENSE
Requires-Dist: requests (>=2.25.1)
